{
  "sources": [
    {
      "title": "GitHub Public Timeline Feed",
      "feedUrl": "https://raw.githubusercontent.com/khulnasoft-lab/feeds/main/github.atom",
      "siteUrl": "https://github.com/khulnasoft",
      "articles": [
        {
          "id": "https://github.com/khulnasoft/Docker-OSX",
          "author": null,
          "description": "khulnasoft\n          \n          forked\n          khulnasoft/Docker-OSX\n          from\n          khulnasoft/Docker-OSX-Archive\n          \n            · May 7, 2025 19:32\n          \n        \nkhulnasoft/Docker-OSX-Archive\n          \n\n          \n\n  Shell\n\n\n              \n\n\n\n              Updated Nov 20, 2024",
          "link": "https://github.com/khulnasoft/Docker-OSX",
          "publishedOn": "2025-05-07T19:32:00.000Z",
          "wordCount": 32978,
          "title": "khulnasoft forked khulnasoft/Docker-OSX from khulnasoft/Docker-OSX-Archive",
          "imageUrl": "https://opengraph.githubassets.com/1d77686e717a0ecc36eb19723ae6e5fb0881a8a296cb10700ca8ae15525de5ac/khulnasoft/Docker-OSX"
        },
        {
          "id": "https://github.com/khulnasoft/StarTerm",
          "author": null,
          "description": "khulnasoft\n          \n          forked\n          khulnasoft/StarTerm\n          from\n          khulnasoft-com/StarTerm\n          \n            · May 7, 2025 18:32\n          \n        \nkhulnasoft-com/StarTerm\n          \nNextShell leverages web technologies to provide a fast, customizable, and multi-platform terminal experience right in your browser.\nUpdated May 7",
          "link": "https://github.com/khulnasoft/StarTerm",
          "publishedOn": "2025-05-07T18:32:17.000Z",
          "wordCount": 835,
          "title": "khulnasoft forked khulnasoft/StarTerm from khulnasoft-com/StarTerm",
          "imageUrl": "https://opengraph.githubassets.com/db1ba83c5972b8529e5c2bab4cb923cd37904d503b68436f5e2bb726f318e2b1/khulnasoft/StarTerm"
        },
        {
          "id": "https://github.com/khulnasoft/github-cherry-pick-action",
          "author": null,
          "description": "khulnasoft\n          \n          forked\n          khulnasoft/github-cherry-pick-action\n          from\n          carloscastrojumo/github-cherry-pick-action\n          \n            · May 5, 2025 23:19\n          \n        \ncarloscastrojumo/github-cherry-pick-action\n          \nGitHub action for cherry pick commits from Pull Requests into Release branchs\n\n  TypeScript\n\n\n              \n\n              \n                  \n                    \n    \n\n58\n              \n\n\n              Updated Mar 10",
          "link": "https://github.com/khulnasoft/github-cherry-pick-action",
          "publishedOn": "2025-05-05T23:19:57.000Z",
          "wordCount": 2936,
          "title": "khulnasoft forked khulnasoft/github-cherry-pick-action from carloscastrojumo/github-cherry-pick-action",
          "imageUrl": "https://opengraph.githubassets.com/9e93f781787de19bab196cf5fc082c459a8722b6343ef03142e5d4557f785b3e/khulnasoft/github-cherry-pick-action"
        },
        {
          "id": "https://github.com/khulnasoft/mio",
          "author": null,
          "description": "khulnasoft\n          \n          forked\n          khulnasoft/mio\n          from\n          tokio-rs/mio\n          \n            · May 5, 2025 20:57\n          \n        \ntokio-rs/mio\n          \nMetal I/O library for Rust.\n\n  Rust\n\n\n              \n\n              \n                  \n                    \n    \n\n6.6k\n              \n\n\n              Updated Apr 15",
          "link": "https://github.com/khulnasoft/mio",
          "publishedOn": "2025-05-05T20:57:25.000Z",
          "wordCount": 4010,
          "title": "khulnasoft forked khulnasoft/mio from tokio-rs/mio",
          "imageUrl": "https://opengraph.githubassets.com/d24e2a16941feda0d9b55148059d45a139310a7e450d47303505a5d7becb9762/khulnasoft/mio"
        },
        {
          "id": "https://github.com/khulnasoft/microsoft-terminal",
          "author": null,
          "description": "khulnasoft\n          \n          forked\n          khulnasoft/microsoft-terminal\n          from\n          microsoft/terminal\n          \n            · May 5, 2025 20:17\n          \n        \nmicrosoft/terminal\n          \nThe new Windows Terminal and the original Windows console host, all in the same place!\n\n  C++\n\n\n              \n\n              \n                  \n                    \n    \n\n98k\n              \n\n              \n                494 issues need help\n              \n\n              Updated May 6",
          "link": "https://github.com/khulnasoft/microsoft-terminal",
          "publishedOn": "2025-05-05T20:17:26.000Z",
          "wordCount": 8643,
          "title": "khulnasoft forked khulnasoft/microsoft-terminal from microsoft/terminal",
          "imageUrl": "https://opengraph.githubassets.com/bada1619d94951a4ae28b1b75bb005697698db44310e5dbbcfd300c8df247dc5/khulnasoft/microsoft-terminal"
        },
        {
          "id": "https://github.com/khulnasoft/vte",
          "author": null,
          "description": "khulnasoft\n          \n          forked\n          khulnasoft/vte\n          from\n          alacritty/vte\n          \n            · May 5, 2025 20:07\n          \n        \nalacritty/vte\n          \nParser for virtual terminal emulators\n\n  Rust\n\n\n              \n\n              \n                  \n                    \n    \n\n266\n              \n\n\n              Updated Apr 8",
          "link": "https://github.com/khulnasoft/vte",
          "publishedOn": "2025-05-05T20:07:44.000Z",
          "wordCount": 934,
          "title": "khulnasoft forked khulnasoft/vte from alacritty/vte",
          "imageUrl": "https://opengraph.githubassets.com/57ed8abf73a62de0584d9aa1f5a43480dd13d415cc1c67957fe90ecb543ed5b7/khulnasoft/vte"
        },
        {
          "id": "https://github.com/khulnasoft/winit",
          "author": null,
          "description": "khulnasoft\n          \n          forked\n          khulnasoft/winit\n          from\n          rust-windowing/winit\n          \n            · May 5, 2025 19:19\n          \n        \nrust-windowing/winit\n          \nWindow handling library in pure Rust\n\n  Rust\n\n\n              \n\n              \n                  \n                    \n    \n\n5.2k\n              \n\n\n              Updated May 5",
          "link": "https://github.com/khulnasoft/winit",
          "publishedOn": "2025-05-05T19:19:39.000Z",
          "wordCount": 2337,
          "title": "khulnasoft forked khulnasoft/winit from rust-windowing/winit",
          "imageUrl": "https://opengraph.githubassets.com/835b0f87cb8f30c7be5450eab597702559d685bf653c1aaf544f457fe095b44a/khulnasoft/winit"
        },
        {
          "id": "https://github.com/khulnasoft/sentry-cocoa",
          "author": null,
          "description": "khulnasoft\n          \n          forked\n          khulnasoft/sentry-cocoa\n          from\n          getsentry/sentry-cocoa\n          \n            · May 5, 2025 19:08\n          \n        \ngetsentry/sentry-cocoa\n          \nThe official Sentry SDK for iOS, tvOS, macOS, watchOS.\n\n  Swift\n\n\n              \n\n              \n                  \n                    \n    \n\n894\n              \n\n\n              Updated May 6",
          "link": "https://github.com/khulnasoft/sentry-cocoa",
          "publishedOn": "2025-05-05T19:08:54.000Z",
          "wordCount": 2105,
          "title": "khulnasoft forked khulnasoft/sentry-cocoa from getsentry/sentry-cocoa",
          "imageUrl": "https://opengraph.githubassets.com/b2c87e3f724e8711eba76eaad98ef8486383b312b7970e1ecea908de862e0084/khulnasoft/sentry-cocoa"
        },
        {
          "id": "https://github.com/khulnasoft/apex",
          "author": null,
          "description": "khulnasoft\n          \n          forked\n          khulnasoft/apex\n          from\n          NVIDIA/apex\n          \n            · April 29, 2025 15:14\n          \n        \nNVIDIA/apex\n          \nA PyTorch Extension: Tools for easy mixed precision and distributed training in Pytorch\n\n  Python\n\n\n              \n\n              \n                  \n                    \n    \n\n8.6k\n              \n\n\n              Updated Apr 11",
          "link": "https://github.com/khulnasoft/apex",
          "publishedOn": "2025-04-29T15:14:15.000Z",
          "wordCount": 4076,
          "title": "khulnasoft forked khulnasoft/apex from NVIDIA/apex",
          "imageUrl": "https://opengraph.githubassets.com/7f5a8254763ac343ae2501f66e878d6274ec26ae1d4c054b20289894e10e6952/khulnasoft/apex"
        },
        {
          "id": "https://github.com/khulnasoft/prerender",
          "author": null,
          "description": "khulnasoft\n          \n          forked\n          khulnasoft/prerender\n          from\n          prerender/prerender\n          \n            · April 27, 2025 11:45\n          \n        \nprerender/prerender\n          \nNode server that uses Headless Chrome to render a javascript-rendered page as HTML. To be used in conjunction with prerender middleware.\n\n  JavaScript\n\n\n              \n\n              \n                  \n                    \n    \n\n6.5k\n              \n\n\n              Updated Sep 12, 2024",
          "link": "https://github.com/khulnasoft/prerender",
          "publishedOn": "2025-04-27T11:45:55.000Z",
          "wordCount": 12227,
          "title": "khulnasoft forked khulnasoft/prerender from prerender/prerender",
          "imageUrl": "https://opengraph.githubassets.com/d571f90e8aa3bbfbd5a799285a3a1ba778cada4a01fe233ed0edd434897ebec3/khulnasoft/prerender"
        },
        {
          "id": "https://github.com/khulnasoft/bazel-central-registry",
          "author": null,
          "description": "khulnasoft\n          \n          forked\n          khulnasoft/bazel-central-registry\n          from\n          bazelbuild/bazel-central-registry\n          \n            · April 26, 2025 09:04\n          \n        \nbazelbuild/bazel-central-registry\n          \nThe central registry of Bazel modules for the Bzlmod external dependency system.\n\n  Starlark\n\n\n              \n\n              \n                  \n                    \n    \n\n287\n              \n\n              \n                2 issues need help\n              \n\n              Updated Apr 26",
          "link": "https://github.com/khulnasoft/bazel-central-registry",
          "publishedOn": "2025-04-26T09:04:28.000Z",
          "wordCount": 1717,
          "title": "khulnasoft forked khulnasoft/bazel-central-registry from bazelbuild/bazel-central-registry",
          "imageUrl": "https://opengraph.githubassets.com/ebf85ea6cd554bf2dfc0b814723be98baee1cda152d0302bc1ba2b986bb282e1/khulnasoft/bazel-central-registry"
        },
        {
          "id": "https://github.com/khulnasoft/macsf-keychain",
          "author": null,
          "description": "khulnasoft\n          \n          forked\n          khulnasoft/macsf-keychain\n          from\n          google/macops-keychainminder\n          \n            · April 25, 2025 15:55\n          \n        \ngoogle/macops-keychainminder\n          \nSecurityAgentPlugin for monitoring keychain password synchronization\n\n  Objective-C\n\n\n              \n\n              \n                  \n                    \n    \n\n95\n              \n\n\n              Updated Dec 13, 2019",
          "link": "https://github.com/khulnasoft/macsf-keychain",
          "publishedOn": "2025-04-25T15:55:06.000Z",
          "wordCount": 2811,
          "title": "khulnasoft forked khulnasoft/macsf-keychain from google/macops-keychainminder",
          "imageUrl": "https://opengraph.githubassets.com/a8973e281256ead51ecf7f4cd6a587b78b3e450b981f40a9976452749bf3e8ea/khulnasoft/macsf-keychain"
        }
      ]
    }
  ],
  "cliVersion": "1.15.1"
}