{
  "sources": [
    {
      "title": "GitHub Public Timeline Feed",
      "feedUrl": "https://raw.githubusercontent.com/khulnasoft-lab/feeds/main/github.atom",
      "siteUrl": "https://github.com/khulnasoft",
      "articles": [
        {
          "id": "https://github.com/khulnasoft/synopkg-recipes",
          "author": null,
          "description": "khulnasoft\n          \n          forked\n          khulnasoft/synopkg-recipes\n          from\n          synopkg/synopkg-recipes\n          \n            · November 8, 2024 08:50\n          \n        \nsynopkg/synopkg-recipes\n          \n\n          \n\n  TypeScript\n\n\n              \n\n\n\n              Updated Nov 8",
          "link": "https://github.com/khulnasoft/synopkg-recipes",
          "publishedOn": "2024-11-08T08:50:25.000Z",
          "wordCount": 2084,
          "title": "khulnasoft forked khulnasoft/synopkg-recipes from synopkg/synopkg-recipes",
          "imageUrl": "https://opengraph.githubassets.com/a9ac559a77900a32db82f2d2122d7d2a9c2cf32e0b69038048776af8afb4d9d2/khulnasoft/synopkg-recipes"
        },
        {
          "id": "https://github.com/khulnasoft/security-vulnogram",
          "author": null,
          "description": "khulnasoft\n          \n          forked\n          khulnasoft/security-vulnogram\n          from\n          Vulnogram/Vulnogram\n          \n            · November 7, 2024 16:24\n          \n        \nVulnogram/Vulnogram\n          \nVulnogram is a tool for creating and editing CVE information in CVE JSON format\n\n  JavaScript\n\n\n              \n\n              \n                  \n                    \n    \n\n161\n              \n\n              \n                3 issues need help\n              \n\n              Updated Oct 31",
          "link": "https://github.com/khulnasoft/security-vulnogram",
          "publishedOn": "2024-11-07T16:24:44.000Z",
          "wordCount": 6591,
          "title": "khulnasoft forked khulnasoft/security-vulnogram from Vulnogram/Vulnogram",
          "imageUrl": "https://opengraph.githubassets.com/0d964b091d8c00d9d3e98c65c2c5f54f19a1e313c8759dbf929e0465e1d14f24/khulnasoft/security-vulnogram"
        },
        {
          "id": "https://github.com/khulnasoft/wrangler-action",
          "author": null,
          "description": "khulnasoft\n          \n          forked\n          khulnasoft/wrangler-action\n          from\n          cloudflare/wrangler-action\n          \n            · November 7, 2024 11:43\n          \n        \ncloudflare/wrangler-action\n          \n🧙‍♀️ easily deploy cloudflare workers applications using wrangler and github actions\n\n  TypeScript\n\n\n              \n\n              \n                  \n                    \n    \n\n1.2k\n              \n\n\n              Updated Nov 7",
          "link": "https://github.com/khulnasoft/wrangler-action",
          "publishedOn": "2024-11-07T11:43:51.000Z",
          "wordCount": 7578,
          "title": "khulnasoft forked khulnasoft/wrangler-action from cloudflare/wrangler-action",
          "imageUrl": "https://opengraph.githubassets.com/fd0d4aa653ed31a2791dc8ba0f1b15bb180be26cf12fdf082642afc28fc85f28/khulnasoft/wrangler-action"
        },
        {
          "id": "https://github.com/khulnasoft/docker-docs",
          "author": null,
          "description": "khulnasoft\n          \n          forked\n          khulnasoft/docker-docs\n          from\n          docker-library/docs\n          \n            · November 7, 2024 02:21\n          \n        \ndocker-library/docs\n          \nDocumentation for Docker Official Images in docker-library\n\n  Shell\n\n\n              \n\n              \n                  \n                    \n    \n\n5.1k\n              \n\n\n              Updated Nov 7",
          "link": "https://github.com/khulnasoft/docker-docs",
          "publishedOn": "2024-11-07T02:21:40.000Z",
          "wordCount": 1576,
          "title": "khulnasoft forked khulnasoft/docker-docs from docker-library/docs",
          "imageUrl": "https://opengraph.githubassets.com/1803686c8be0812b1173895451b27ce1d6da746e88ead3bdeb98c3c1cd2ee308/khulnasoft/docker-docs"
        },
        {
          "id": "https://github.com/khulnasoft/metadata-service",
          "author": null,
          "description": "khulnasoft\n      \n      added\n      FortiShield\n      to\n      khulnasoft/metadata-service\n      \n        · October 31, 2024 22:12",
          "link": "https://github.com/khulnasoft/metadata-service",
          "publishedOn": "2024-10-31T22:12:17.000Z",
          "wordCount": 4437,
          "title": "khulnasoft added FortiShield to khulnasoft/metadata-service",
          "imageUrl": "https://opengraph.githubassets.com/007f250de1a6be44ea0a7b22632266e33160aea94c31e7c9e285e8234e867b6e/khulnasoft/metadata-service"
        },
        {
          "id": "https://github.com/khulnasoft/interpreter",
          "author": null,
          "description": "khulnasoft\n      \n      added\n      FortiShield\n      to\n      khulnasoft/interpreter\n      \n        · October 26, 2024 16:43",
          "link": "https://github.com/khulnasoft/interpreter",
          "publishedOn": "2024-10-26T16:43:02.000Z",
          "wordCount": 8949,
          "title": "khulnasoft added FortiShield to khulnasoft/interpreter",
          "imageUrl": "https://opengraph.githubassets.com/e08e5c0599122dd9011de1a9b31d55ee4fdb200cdbab106f47588a6514db37b3/khulnasoft/interpreter"
        },
        {
          "id": "https://github.com/khulnasoft/open-interpreter",
          "author": null,
          "description": "khulnasoft\n      \n      added\n      FortiShield\n      to\n      khulnasoft/open-interpreter\n      \n        · October 26, 2024 16:41",
          "link": "https://github.com/khulnasoft/open-interpreter",
          "publishedOn": "2024-10-26T16:41:12.000Z",
          "wordCount": 8962,
          "title": "khulnasoft added FortiShield to khulnasoft/open-interpreter",
          "imageUrl": "https://opengraph.githubassets.com/eb70959b76f34adf77b47010e69cea55a9b74e0f0ea635fb86098d5f43f77dfb/khulnasoft/open-interpreter"
        },
        {
          "id": "https://github.com/khulnasoft/open-interpreter",
          "author": null,
          "description": "khulnasoft\n          \n          forked\n          khulnasoft/open-interpreter\n          from\n          OpenInterpreter/open-interpreter\n          \n            · October 26, 2024 16:41\n          \n        \nOpenInterpreter/open-interpreter\n          \nA natural language interface for computers\n\n  Python\n\n\n              \n\n              \n                  \n                    \n    \n\n53.8k\n              \n\n\n              Updated Oct 26",
          "link": "https://github.com/khulnasoft/open-interpreter",
          "publishedOn": "2024-10-26T16:41:12.000Z",
          "wordCount": 8962,
          "title": "khulnasoft forked khulnasoft/open-interpreter from OpenInterpreter/open-interpreter",
          "imageUrl": "https://opengraph.githubassets.com/eb70959b76f34adf77b47010e69cea55a9b74e0f0ea635fb86098d5f43f77dfb/khulnasoft/open-interpreter"
        },
        {
          "id": "https://github.com/khulnasoft/vercel_ai",
          "author": null,
          "description": "khulnasoft\n      \n      added\n      FortiShield\n      to\n      khulnasoft/vercel_ai\n      \n        · October 26, 2024 16:39",
          "link": "https://github.com/khulnasoft/vercel_ai",
          "publishedOn": "2024-10-26T16:39:39.000Z",
          "wordCount": 4148,
          "title": "khulnasoft added FortiShield to khulnasoft/vercel_ai",
          "imageUrl": "https://opengraph.githubassets.com/478244af74666e155cb01c82b844fa952bc9b97b2bc0e56c0ce882f4cb138764/khulnasoft/vercel_ai"
        },
        {
          "id": "https://github.com/khulnasoft/vercel_ai",
          "author": null,
          "description": "khulnasoft\n          \n          forked\n          khulnasoft/vercel_ai\n          from\n          vercel/ai\n          \n            · October 26, 2024 16:39\n          \n        \nvercel/ai\n          \nBuild AI-powered applications with React, Svelte, Vue, and Solid\n\n  TypeScript\n\n\n              \n\n              \n                  \n                    \n    \n\n9.8k\n              \n\n              \n                10 issues need help\n              \n\n              Updated Oct 26",
          "link": "https://github.com/khulnasoft/vercel_ai",
          "publishedOn": "2024-10-26T16:39:38.000Z",
          "wordCount": 4148,
          "title": "khulnasoft forked khulnasoft/vercel_ai from vercel/ai",
          "imageUrl": "https://opengraph.githubassets.com/478244af74666e155cb01c82b844fa952bc9b97b2bc0e56c0ce882f4cb138764/khulnasoft/vercel_ai"
        },
        {
          "id": "https://github.com/khulnasoft/CAPE-Community",
          "author": null,
          "description": "khulnasoft\n          \n          forked\n          khulnasoft/CAPE-Community\n          from\n          CAPESandbox/community\n          \n            · October 24, 2024 23:08\n          \n        \nCAPESandbox/community\n          \nCommunity modules for CAPE Sandbox\n\n  Python\n\n\n              \n\n              \n                  \n                    \n    \n\n85\n              \n\n\n              Updated Oct 9",
          "link": "https://github.com/khulnasoft/CAPE-Community",
          "publishedOn": "2024-10-24T23:08:00.000Z",
          "wordCount": 2048,
          "title": "khulnasoft forked khulnasoft/CAPE-Community from CAPESandbox/community",
          "imageUrl": "https://opengraph.githubassets.com/92cfa8dbe2dfb6aa994ef01ca3b5b8e38b9f97532abfbbf23b876d3b97eb746d/khulnasoft/CAPE-Community"
        },
        {
          "id": "https://github.com/khulnasoft/copilot-cli-local",
          "author": null,
          "description": "khulnasoft\n          \n          forked\n          khulnasoft/copilot-cli-local\n          from\n          aws/copilot-cli\n          \n            · October 24, 2024 13:08\n          \n        \naws/copilot-cli\n          \nThe AWS Copilot CLI is a tool for developers to build, release and operate production ready containerized applications on AWS App Runner or Amazon …\n\n  Go\n\n\n              \n\n              \n                  \n                    \n    \n\n3.5k\n              \n\n\n              Updated Oct 7",
          "link": "https://github.com/khulnasoft/copilot-cli-local",
          "publishedOn": "2024-10-24T13:08:41.000Z",
          "wordCount": 3420,
          "title": "khulnasoft forked khulnasoft/copilot-cli-local from aws/copilot-cli",
          "imageUrl": "https://opengraph.githubassets.com/dab84132b39ba7c594e16605dfac5f3a22fd3bd2d11b2ca54b811988e2fbce40/khulnasoft/copilot-cli-local"
        },
        {
          "id": "https://github.com/khulnasoft/serverless-examples",
          "author": null,
          "description": "khulnasoft\n          \n          forked\n          khulnasoft/serverless-examples\n          from\n          serverless/examples\n          \n            · October 24, 2024 13:07\n          \n        \nserverless/examples\n          \nServerless Examples – A collection of boilerplates and examples of serverless architectures built with the Serverless Framework on AWS Lambda, Micr…\n\n  JavaScript\n\n\n              \n\n              \n                  \n                    \n    \n\n11.4k\n              \n\n              \n                7 issues need help\n              \n\n              Updated Sep 18",
          "link": "https://github.com/khulnasoft/serverless-examples",
          "publishedOn": "2024-10-24T13:07:07.000Z",
          "wordCount": 13406,
          "title": "khulnasoft forked khulnasoft/serverless-examples from serverless/examples",
          "imageUrl": "https://opengraph.githubassets.com/03250edeb10f9c84034ae079970de0e594c69cd6cb926b03f8a8b2749f48c634/khulnasoft/serverless-examples"
        },
        {
          "id": "https://github.com/khulnasoft/devcontainers.github.io",
          "author": null,
          "description": "khulnasoft\n          \n          forked\n          khulnasoft/devcontainers.github.io\n          from\n          devcontainers/devcontainers.github.io\n          \n            · October 24, 2024 12:53\n          \n        \ndevcontainers/devcontainers.github.io\n          \nWeb content for the development containers specification.\n\n  HTML\n\n\n              \n\n              \n                  \n                    \n    \n\n121\n              \n\n\n              Updated Oct 8",
          "link": "https://github.com/khulnasoft/devcontainers.github.io",
          "publishedOn": "2024-10-24T12:53:00.000Z",
          "wordCount": 2718,
          "title": "khulnasoft forked khulnasoft/devcontainers.github.io from devcontainers/devcontainers.github.io",
          "imageUrl": "https://opengraph.githubassets.com/cf495299ccfef577de75f121e89b4b01240706a7f1fd2a5dbea222c614418d4d/khulnasoft/devcontainers.github.io"
        },
        {
          "id": "https://github.com/khulnasoft/moto",
          "author": null,
          "description": "khulnasoft\n          \n          forked\n          khulnasoft/moto\n          from\n          getmoto/moto\n          \n            · October 24, 2024 12:20\n          \n        \ngetmoto/moto\n          \nA library that allows you to easily mock out tests based on AWS infrastructure.\n\n  Python\n\n\n              \n\n              \n                  \n                    \n    \n\n7.6k\n              \n\n\n              Updated Oct 24",
          "link": "https://github.com/khulnasoft/moto",
          "publishedOn": "2024-10-24T12:20:54.000Z",
          "wordCount": 1605,
          "title": "khulnasoft forked khulnasoft/moto from getmoto/moto",
          "imageUrl": "https://opengraph.githubassets.com/3c6c92f42df903a6e9fd17385e27d31d288ca2d942b571f94bf7b787d78a57e5/khulnasoft/moto"
        },
        {
          "id": "https://github.com/khulnasoft/khulnasoft-flake",
          "author": null,
          "description": "khulnasoft\n      \n      added\n      FortiShield\n      to\n      khulnasoft/khulnasoft-flake\n      \n        · October 23, 2024 23:45",
          "link": "https://github.com/khulnasoft/khulnasoft-flake",
          "publishedOn": "2024-10-23T23:45:28.000Z",
          "wordCount": 1559,
          "title": "khulnasoft added FortiShield to khulnasoft/khulnasoft-flake",
          "imageUrl": "https://opengraph.githubassets.com/a6513eb86af5832805e46b2927c45481100ffd1bf443807ac22cf56d084147af/khulnasoft/khulnasoft-flake"
        },
        {
          "id": "https://github.com/khulnasoft/webhooks",
          "author": null,
          "description": "khulnasoft\n      \n      added\n      FortiShield\n      to\n      khulnasoft/webhooks\n      \n        · October 23, 2024 23:34",
          "link": "https://github.com/khulnasoft/webhooks",
          "publishedOn": "2024-10-23T23:34:25.000Z",
          "wordCount": 1613,
          "title": "khulnasoft added FortiShield to khulnasoft/webhooks",
          "imageUrl": "https://opengraph.githubassets.com/89f80c6398862570680114684b2ee914cc73232a77c28735869d7d03c80527ac/khulnasoft/webhooks"
        },
        {
          "id": "https://github.com/khulnasoft/misp-objects",
          "author": null,
          "description": "khulnasoft\n          \n          forked\n          khulnasoft/misp-objects\n          from\n          MISP/misp-objects\n          \n            · October 23, 2024 13:01\n          \n        \nMISP/misp-objects\n          \nDefinition, description and relationship types of MISP objects \n\n  Python\n\n\n              \n\n              \n                  \n                    \n    \n\n91\n              \n\n\n              Updated Oct 17",
          "link": "https://github.com/khulnasoft/misp-objects",
          "publishedOn": "2024-10-23T13:01:02.000Z",
          "wordCount": 16003,
          "title": "khulnasoft forked khulnasoft/misp-objects from MISP/misp-objects",
          "imageUrl": "https://opengraph.githubassets.com/8ec4c37b676d5d632c6a7f7f24cde42f4931bbb6bdd5dbb34a642a5ff41736b8/khulnasoft/misp-objects"
        },
        {
          "id": "https://github.com/khulnasoft/PowerPlatformConnectors",
          "author": null,
          "description": "khulnasoft\n          \n          forked\n          khulnasoft/PowerPlatformConnectors\n          from\n          microsoft/PowerPlatformConnectors\n          \n            · October 23, 2024 12:58\n          \n        \nmicrosoft/PowerPlatformConnectors\n          \nThis is a repository for Microsoft Power Automate, Power Apps, and Azure Logic Apps connectors\n\n  C#\n\n\n              \n\n              \n                  \n                    \n    \n\n975\n              \n\n\n              Updated Oct 23",
          "link": "https://github.com/khulnasoft/PowerPlatformConnectors",
          "publishedOn": "2024-10-23T12:58:24.000Z",
          "wordCount": 7250,
          "title": "khulnasoft forked khulnasoft/PowerPlatformConnectors from microsoft/PowerPlatformConnectors",
          "imageUrl": "https://opengraph.githubassets.com/d722eae30904e2d78d6f6b32ff2f546843eb04db4329dd49aa526bf1ed5dbcce/khulnasoft/PowerPlatformConnectors"
        },
        {
          "id": "https://github.com/boss-net/go-licenses/pull/1",
          "author": null,
          "description": "khulnasoft\n          \n          closed\n          boss-net/go-licenses#1\n          \n            · October 19, 2024 20:49\n          \n        \n\n\n\n      \n[pull] master from khulnasoft:master\n          #1\n            \nSee Commits and Changes for more details.\n\nCreated by  pull[bot]\nCan you help keep this open source service alive? 💖 Please sponsor : )\n+3,378\n            -23,704",
          "link": "https://github.com/boss-net/go-licenses/pull/1",
          "publishedOn": "2024-10-19T20:49:06.000Z",
          "wordCount": 762,
          "title": "khulnasoft closed a pull request in boss-net/go-licenses",
          "imageUrl": "https://opengraph.githubassets.com/99bc076d9b167cb2b873fb8710468b2d8deadc2278ba1229e153500ced4e9b3c/boss-net/go-licenses/pull/1"
        },
        {
          "id": "https://github.com/khulnasoft/synopkg",
          "author": null,
          "description": "khulnasoft\n          \n          forked\n          khulnasoft/synopkg\n          from\n          synopkg/synopkg\n          \n            · October 19, 2024 20:35\n          \n        \nsynopkg/synopkg\n          \n\n          \n\n  TypeScript\n\n\n              \n\n\n\n              Updated Oct 19",
          "link": "https://github.com/khulnasoft/synopkg",
          "publishedOn": "2024-10-19T20:35:48.000Z",
          "wordCount": 3300,
          "title": "khulnasoft forked khulnasoft/synopkg from synopkg/synopkg",
          "imageUrl": "https://opengraph.githubassets.com/35ae5fa84e3b2413029d697304d6b3d49b9ce3303b61aa0950dd9b00ec67ae78/khulnasoft/synopkg"
        },
        {
          "id": "https://github.com/khulnasoft/netdatax",
          "author": null,
          "description": "khulnasoft\n          \n          forked\n          khulnasoft/netdatax\n          from\n          netdata/netdata\n          \n            · October 18, 2024 23:26\n          \n        \nnetdata/netdata\n          \nArchitected for speed. Automated for easy. Monitoring and troubleshooting, transformed!\n\n  C\n\n\n              \n\n              \n                  \n                    \n    \n\n71.6k\n              \n\n              \n                3 issues need help\n              \n\n              Updated Oct 19",
          "link": "https://github.com/khulnasoft/netdatax",
          "publishedOn": "2024-10-18T23:26:38.000Z",
          "wordCount": 21089,
          "title": "khulnasoft forked khulnasoft/netdatax from netdata/netdata",
          "imageUrl": "https://opengraph.githubassets.com/bef98fa83dd778bd8dd6156d44d2f0d40db110e3a0dc9f121897b1cb9125f374/khulnasoft/netdata"
        },
        {
          "id": "https://github.com/khulnasoft/libbpf",
          "author": null,
          "description": "khulnasoft\n          \n          forked\n          khulnasoft/libbpf\n          from\n          libbpf/libbpf\n          \n            · October 18, 2024 23:09\n          \n        \nlibbpf/libbpf\n          \nAutomated upstream mirror for libbpf stand-alone build.\n\n  C\n\n\n              \n\n              \n                  \n                    \n    \n\n2.2k\n              \n\n\n              Updated Oct 11",
          "link": "https://github.com/khulnasoft/libbpf",
          "publishedOn": "2024-10-18T23:09:41.000Z",
          "wordCount": 4159,
          "title": "khulnasoft forked khulnasoft/libbpf from libbpf/libbpf",
          "imageUrl": "https://opengraph.githubassets.com/60e72d8e878c4c1bebd9b54156454b6bb5fc820a0c12d0c3f58ed28c68d24271/khulnasoft/libbpf"
        },
        {
          "id": "https://github.com/khulnasoft/codetypo-actions",
          "author": null,
          "description": "khulnasoft\n      \n      added\n      FortiShield\n      to\n      khulnasoft/codetypo-actions\n      \n        · October 18, 2024 19:02",
          "link": "https://github.com/khulnasoft/codetypo-actions",
          "publishedOn": "2024-10-18T19:02:28.000Z",
          "wordCount": 4057,
          "title": "khulnasoft added FortiShield to khulnasoft/codetypo-actions",
          "imageUrl": "https://opengraph.githubassets.com/7a06de82ff43475cb9c4f173af3308a8a892532c40590727790bc9ccaa0e7d81/khulnasoft/codetypo-actions"
        },
        {
          "id": "https://github.com/khulnasoft/Discourse-easy-footer",
          "author": null,
          "description": "khulnasoft\n          \n          forked\n          khulnasoft/Discourse-easy-footer\n          from\n          discourse/Discourse-easy-footer\n          \n            · October 15, 2024 02:39\n          \n        \ndiscourse/Discourse-easy-footer\n          \n\n          \n\n  JavaScript\n\n\n              \n\n              \n                  \n                    \n    \n\n14\n              \n\n\n              Updated Oct 14",
          "link": "https://github.com/khulnasoft/Discourse-easy-footer",
          "publishedOn": "2024-10-15T02:39:00.000Z",
          "wordCount": 1520,
          "title": "khulnasoft forked khulnasoft/Discourse-easy-footer from discourse/Discourse-easy-footer",
          "imageUrl": "https://opengraph.githubassets.com/3b67a615c014c0d5750975129452c086bcd5639b33a5ddedaace5e3a03053896/khulnasoft/Discourse-easy-footer"
        },
        {
          "id": "https://github.com/khulnasoft/discourse-google-font-component",
          "author": null,
          "description": "khulnasoft\n          \n          forked\n          khulnasoft/discourse-google-font-component\n          from\n          discourse/discourse-google-font-component\n          \n            · October 15, 2024 02:38\n          \n        \ndiscourse/discourse-google-font-component\n          \n\n          \n\n  SCSS\n\n\n              \n\n              \n                  \n                    \n    \n\n1\n              \n\n\n              Updated Oct 14",
          "link": "https://github.com/khulnasoft/discourse-google-font-component",
          "publishedOn": "2024-10-15T02:38:12.000Z",
          "wordCount": 1577,
          "title": "khulnasoft forked khulnasoft/discourse-google-font-component from discourse/discourse-google-font-component",
          "imageUrl": "https://opengraph.githubassets.com/659f7548267cd838f89f9f6b0eefc0c3ce4d4d58d09302d66882397403924174/khulnasoft/discourse-google-font-component"
        },
        {
          "id": "https://github.com/khulnasoft/discourse-brand-header",
          "author": null,
          "description": "khulnasoft\n          \n          forked\n          khulnasoft/discourse-brand-header\n          from\n          discourse/discourse-brand-header\n          \n            · October 15, 2024 02:37\n          \n        \ndiscourse/discourse-brand-header\n          \nBrand header theme component for Discourse\n\n  JavaScript\n\n\n              \n\n              \n                  \n                    \n    \n\n29\n              \n\n\n              Updated Oct 14",
          "link": "https://github.com/khulnasoft/discourse-brand-header",
          "publishedOn": "2024-10-15T02:37:17.000Z",
          "wordCount": 1572,
          "title": "khulnasoft forked khulnasoft/discourse-brand-header from discourse/discourse-brand-header",
          "imageUrl": "https://opengraph.githubassets.com/6a6b6a8ad581cac81bd081a85f534e3315c649eed64a2595d5ff3bccd2b8e786/khulnasoft/discourse-brand-header"
        },
        {
          "id": "https://github.com/khulnasoft/meshplay-consul",
          "author": null,
          "description": "khulnasoft\n          \n          forked\n          khulnasoft/meshplay-consul\n          from\n          synopkg/meshplay-consul\n          \n            · October 13, 2024 17:33\n          \n        \nsynopkg/meshplay-consul\n          \n\n          \n\n  Go\n\n\n              \n\n\n\n              Updated Oct 13",
          "link": "https://github.com/khulnasoft/meshplay-consul",
          "publishedOn": "2024-10-13T17:33:54.000Z",
          "wordCount": 2390,
          "title": "khulnasoft forked khulnasoft/meshplay-consul from synopkg/meshplay-consul",
          "imageUrl": "https://opengraph.githubassets.com/b460fec244bb396b5fbf80bc0d13466e1176f4acc31c83764622cc32a49ce43e/khulnasoft/meshplay-consul"
        },
        {
          "id": "https://github.com/khulnasoft/uv",
          "author": null,
          "description": "khulnasoft\n          \n          forked\n          khulnasoft/uv\n          from\n          astral-sh/uv\n          \n            · October 12, 2024 19:04\n          \n        \nastral-sh/uv\n          \nAn extremely fast Python package and project manager, written in Rust.\n\n  Rust\n\n\n              \n\n              \n                  \n                    \n    \n\n22.7k\n              \n\n              \n                49 issues need help\n              \n\n              Updated Oct 12",
          "link": "https://github.com/khulnasoft/uv",
          "publishedOn": "2024-10-12T19:04:16.000Z",
          "wordCount": 5491,
          "title": "khulnasoft forked khulnasoft/uv from astral-sh/uv",
          "imageUrl": "https://opengraph.githubassets.com/024dafb0173b02601ab3e27cd4b6f9a1c24aae80449b0ab3940e92ac1fd61c50/khulnasoft/uv"
        },
        {
          "id": "https://github.com/khulnasoft/markdown",
          "author": null,
          "description": "khulnasoft\n          \n          forked\n          khulnasoft/markdown\n          from\n          Python-Markdown/markdown\n          \n            · October 12, 2024 19:01\n          \n        \nPython-Markdown/markdown\n          \nA Python implementation of John Gruber’s Markdown with Extension support.\n\n  Python\n\n\n              \n\n              \n                  \n                    \n    \n\n3.8k\n              \n\n\n              Updated Oct 1",
          "link": "https://github.com/khulnasoft/markdown",
          "publishedOn": "2024-10-12T19:01:31.000Z",
          "wordCount": 2332,
          "title": "khulnasoft forked khulnasoft/markdown from Python-Markdown/markdown",
          "imageUrl": "https://opengraph.githubassets.com/c127b24e08371387889e23557faa73f8f2b8c479318b33139c8d709c0b3f16a4/khulnasoft/markdown"
        },
        {
          "id": "https://github.com/khulnasoft/automation-working-group",
          "author": null,
          "description": "khulnasoft\n          \n          forked\n          khulnasoft/automation-working-group\n          from\n          CVEProject/automation-working-group\n          \n            · October 9, 2024 01:58\n          \n        \nCVEProject/automation-working-group\n          \nCVE Automation Working Group\n\n160\n              \n\n\n              Updated Oct 9",
          "link": "https://github.com/khulnasoft/automation-working-group",
          "publishedOn": "2024-10-09T01:58:32.000Z",
          "wordCount": 2289,
          "title": "khulnasoft forked khulnasoft/automation-working-group from CVEProject/automation-working-group",
          "imageUrl": "https://opengraph.githubassets.com/b5a5fbe3bd2817933cea6f440f7defb3e23011847b3e393bf3e7dae3dfedfaa7/khulnasoft/automation-working-group"
        },
        {
          "id": "https://github.com/khulnasoft/tree-sitter-python",
          "author": null,
          "description": "khulnasoft\n          \n          forked\n          khulnasoft/tree-sitter-python\n          from\n          tree-sitter/tree-sitter-python\n          \n            · October 4, 2024 15:30\n          \n        \ntree-sitter/tree-sitter-python\n          \nPython grammar for tree-sitter\n\n  JavaScript\n\n\n              \n\n              \n                  \n                    \n    \n\n361\n              \n\n              \n                1 issue needs help\n              \n\n              Updated Sep 3",
          "link": "https://github.com/khulnasoft/tree-sitter-python",
          "publishedOn": "2024-10-04T15:30:19.000Z",
          "wordCount": 1830,
          "title": "khulnasoft forked khulnasoft/tree-sitter-python from tree-sitter/tree-sitter-python",
          "imageUrl": "https://opengraph.githubassets.com/fffccaea7051de825c1315291650beaa7ea48b3976b62b9c97342069290b719a/khulnasoft/tree-sitter-python"
        },
        {
          "id": "https://github.com/khulnasoft/archiver",
          "author": null,
          "description": "khulnasoft\n          \n          forked\n          khulnasoft/archiver\n          from\n          mholt/archiver\n          \n            · October 1, 2024 07:59\n          \n        \nmholt/archiver\n          \nEasily create & extract archives, and compress & decompress files of various formats\n\n  Go\n\n\n              \n\n              \n                  \n                    \n    \n\n4.3k\n              \n\n              \n                1 issue needs help\n              \n\n              Updated Sep 24",
          "link": "https://github.com/khulnasoft/archiver",
          "publishedOn": "2024-10-01T07:59:39.000Z",
          "wordCount": 6900,
          "title": "khulnasoft forked khulnasoft/archiver from mholt/archiver",
          "imageUrl": "https://opengraph.githubassets.com/01d947c8027ec3e46b155090951b5803249a8e0ea43967d33e4b79ebbd3cbf22/khulnasoft/archiver"
        },
        {
          "id": "https://github.com/khulnasoft/dotdev",
          "author": null,
          "description": "khulnasoft\n      \n      added\n      FortiShield\n      to\n      khulnasoft/dotdev\n      \n        · September 30, 2024 11:08",
          "link": "https://github.com/khulnasoft/dotdev",
          "publishedOn": "2024-09-30T11:08:11.000Z",
          "wordCount": 2167,
          "title": "khulnasoft added FortiShield to khulnasoft/dotdev",
          "imageUrl": "https://opengraph.githubassets.com/7d73829906176f33b1929868363c3e5a914d97501ec929a866c4a455ec407bf0/khulnasoft/dotdev"
        },
        {
          "id": "https://github.com/khulnasoft/repo2docker",
          "author": null,
          "description": "khulnasoft\n      \n      added\n      FortiShield\n      to\n      khulnasoft/repo2docker\n      \n        · September 30, 2024 06:17",
          "link": "https://github.com/khulnasoft/repo2docker",
          "publishedOn": "2024-09-30T06:17:08.000Z",
          "wordCount": 3269,
          "title": "khulnasoft added FortiShield to khulnasoft/repo2docker",
          "imageUrl": "https://opengraph.githubassets.com/4f73f81cabe526a25e9371e7074094713752cf99c62ad3a3ccbe3d01475e5758/khulnasoft/repo2docker"
        },
        {
          "id": "https://github.com/khulnasoft/repo2docker",
          "author": null,
          "description": "khulnasoft\n          \n          forked\n          khulnasoft/repo2docker\n          from\n          khulnasoft/jupyter-repo2docker\n          \n            · September 30, 2024 06:17\n          \n        \nkhulnasoft/jupyter-repo2docker\n          \nTurn repositories into Jupyter-enabled Docker images\nUpdated Sep 16",
          "link": "https://github.com/khulnasoft/repo2docker",
          "publishedOn": "2024-09-30T06:17:08.000Z",
          "wordCount": 3269,
          "title": "khulnasoft forked khulnasoft/repo2docker from khulnasoft/jupyter-repo2docker",
          "imageUrl": "https://opengraph.githubassets.com/4f73f81cabe526a25e9371e7074094713752cf99c62ad3a3ccbe3d01475e5758/khulnasoft/repo2docker"
        },
        {
          "id": "https://github.com/khulnasoft/jupyter-repo2docker",
          "author": null,
          "description": "khulnasoft\n      \n      added\n      FortiShield\n      to\n      khulnasoft/jupyter-repo2docker\n      \n        · September 30, 2024 06:15",
          "link": "https://github.com/khulnasoft/jupyter-repo2docker",
          "publishedOn": "2024-09-30T06:15:44.000Z",
          "wordCount": null,
          "title": "khulnasoft added FortiShield to khulnasoft/jupyter-repo2docker",
          "imageUrl": null
        },
        {
          "id": "https://github.com/khulnasoft/jupyter-repo2docker",
          "author": null,
          "description": "khulnasoft\n          \n          forked\n          khulnasoft/jupyter-repo2docker\n          from\n          jupyterhub/repo2docker\n          \n            · September 30, 2024 06:15\n          \n        \njupyterhub/repo2docker\n          \nTurn repositories into Jupyter-enabled Docker images\n\n  Python\n\n\n              \n\n              \n                  \n                    \n    \n\n1.6k\n              \n\n              \n                15 issues need help\n              \n\n              Updated Sep 16",
          "link": "https://github.com/khulnasoft/jupyter-repo2docker",
          "publishedOn": "2024-09-30T06:15:44.000Z",
          "wordCount": null,
          "title": "khulnasoft forked khulnasoft/jupyter-repo2docker from jupyterhub/repo2docker",
          "imageUrl": null
        },
        {
          "id": "https://github.com/khulnasoft/repo2docker",
          "author": null,
          "description": "khulnasoft\n      \n      added\n      FortiShield\n      to\n      khulnasoft/repo2docker\n      \n        · September 30, 2024 05:48",
          "link": "https://github.com/khulnasoft/repo2docker",
          "publishedOn": "2024-09-30T05:48:27.000Z",
          "wordCount": 3269,
          "title": "khulnasoft added FortiShield to khulnasoft/repo2docker",
          "imageUrl": "https://opengraph.githubassets.com/4f73f81cabe526a25e9371e7074094713752cf99c62ad3a3ccbe3d01475e5758/khulnasoft/repo2docker"
        },
        {
          "id": "https://github.com/khulnasoft/devenv",
          "author": null,
          "description": "khulnasoft\n      \n      added\n      FortiShield\n      to\n      khulnasoft/devenv\n      \n        · September 30, 2024 02:48",
          "link": "https://github.com/khulnasoft/devenv",
          "publishedOn": "2024-09-30T02:48:54.000Z",
          "wordCount": null,
          "title": "khulnasoft added FortiShield to khulnasoft/devenv",
          "imageUrl": null
        },
        {
          "id": "https://github.com/khulnasoft/docs",
          "author": null,
          "description": "khulnasoft\n      \n      added\n      FortiShield\n      to\n      khulnasoft/docs\n      \n        · September 29, 2024 19:15",
          "link": "https://github.com/khulnasoft/docs",
          "publishedOn": "2024-09-29T19:15:12.000Z",
          "wordCount": 347,
          "title": "khulnasoft added FortiShield to khulnasoft/docs",
          "imageUrl": "https://opengraph.githubassets.com/7e67a07e71597f164a107f448923e4f580545a5f880d2aa7200a30cd50b286c7/khulnasoft/docs"
        },
        {
          "id": "https://github.com/khulnasoft/kengine-dist",
          "author": null,
          "description": "khulnasoft\n      \n      added\n      FortiShield\n      to\n      khulnasoft/kengine-dist\n      \n        · September 29, 2024 00:33",
          "link": "https://github.com/khulnasoft/kengine-dist",
          "publishedOn": "2024-09-29T00:33:37.000Z",
          "wordCount": 1532,
          "title": "khulnasoft added FortiShield to khulnasoft/kengine-dist",
          "imageUrl": "https://opengraph.githubassets.com/2fc1118df542cc2b0c605a3cc3a18bf4e0ee1b3818c7d90b5c0dcf8803fdb2f9/khulnasoft/kengine-dist"
        },
        {
          "id": "https://github.com/khulnasoft/dockyard",
          "author": null,
          "description": "khulnasoft\n      \n      added\n      FortiShield\n      to\n      khulnasoft/dockyard\n      \n        · September 28, 2024 18:40",
          "link": "https://github.com/khulnasoft/dockyard",
          "publishedOn": "2024-09-28T18:40:17.000Z",
          "wordCount": 4135,
          "title": "khulnasoft added FortiShield to khulnasoft/dockyard",
          "imageUrl": "https://opengraph.githubassets.com/f37ca5bba2c7f3bda1e0ae17d7c80e072abfdf0c7cd7f51d8c87871d4f9dab90/khulnasoft/dockyard"
        },
        {
          "id": "https://github.com/khulnasoft/dockyard-dev",
          "author": null,
          "description": "khulnasoft\n      \n      added\n      FortiShield\n      to\n      khulnasoft/dockyard-dev\n      \n        · September 28, 2024 18:38",
          "link": "https://github.com/khulnasoft/dockyard-dev",
          "publishedOn": "2024-09-28T18:38:48.000Z",
          "wordCount": 2614,
          "title": "khulnasoft added FortiShield to khulnasoft/dockyard-dev",
          "imageUrl": "https://opengraph.githubassets.com/743548f19b4381fef110fa1f72d42c29975de0b7fd5e281c4b088fc7f02104cc/khulnasoft/dockyard-dev"
        },
        {
          "id": "https://github.com/khulnasoft/tunnel",
          "author": null,
          "description": "khulnasoft\n          \n          forked\n          khulnasoft/tunnel\n          from\n          khulnasoft/trivy\n          \n            · September 27, 2024 20:37\n          \n        \nkhulnasoft/trivy\n          \nFind vulnerabilities, misconfigurations, secrets, SBOM in containers, Kubernetes, code repositories, clouds and more\n\n  Go\n\n\n              \n\n\n\n              Updated Sep 27",
          "link": "https://github.com/khulnasoft/tunnel",
          "publishedOn": "2024-09-27T20:37:30.000Z",
          "wordCount": 3598,
          "title": "khulnasoft forked khulnasoft/tunnel from khulnasoft/trivy",
          "imageUrl": "https://opengraph.githubassets.com/475dd5a3e7a00d98cff8ea9b12233eef9dc14173f06a51b531e5479eddff79a7/khulnasoft/tunnel"
        },
        {
          "id": "https://github.com/khulnasoft/khulnasoft-repo",
          "author": null,
          "description": "khulnasoft\n      \n      added\n      FortiShield\n      to\n      khulnasoft/khulnasoft-repo\n      \n        · September 25, 2024 16:40",
          "link": "https://github.com/khulnasoft/khulnasoft-repo",
          "publishedOn": "2024-09-25T16:40:17.000Z",
          "wordCount": 3478,
          "title": "khulnasoft added FortiShield to khulnasoft/khulnasoft-repo",
          "imageUrl": "https://opengraph.githubassets.com/46b6f50dc74776b4912cc20251433071de2f670a14f1f4c4ce1b2ce4aa2566e1/khulnasoft/khulnasoft-repo"
        },
        {
          "id": "https://github.com/khulnasoft/runner-images-temp",
          "author": null,
          "description": "khulnasoft\n          \n          forked\n          khulnasoft/runner-images-temp\n          from\n          khulnasoft/runner-images\n          \n            · September 25, 2024 15:21\n          \n        \nkhulnasoft/runner-images\n          \n\n          \n\n  PowerShell\n\n\n              \n\n\n\n              Updated Sep 25",
          "link": "https://github.com/khulnasoft/runner-images-temp",
          "publishedOn": "2024-09-25T15:21:51.000Z",
          "wordCount": 6936,
          "title": "khulnasoft forked khulnasoft/runner-images-temp from khulnasoft/runner-images",
          "imageUrl": "https://opengraph.githubassets.com/041c117d473fc91f3f8969ea427cd5db46932a576c92d215a62c7c968f4c5231/khulnasoft/runner-images-temp"
        },
        {
          "id": "https://github.com/khulnasoft/Docker-Provider",
          "author": null,
          "description": "khulnasoft\n      \n      added\n      FortiShield\n      to\n      khulnasoft/Docker-Provider\n      \n        · September 25, 2024 14:06",
          "link": "https://github.com/khulnasoft/Docker-Provider",
          "publishedOn": "2024-09-25T14:06:34.000Z",
          "wordCount": 13562,
          "title": "khulnasoft added FortiShield to khulnasoft/Docker-Provider",
          "imageUrl": "https://opengraph.githubassets.com/a11d617f8c81289a31c09e9285dc81cb232060777c0c9edf730af66468359538/khulnasoft/Docker-Provider"
        },
        {
          "id": "https://github.com/khulnasoft/codetypo-validator",
          "author": null,
          "description": "khulnasoft\n      \n      added\n      FortiShield\n      to\n      khulnasoft/codetypo-validator\n      \n        · September 24, 2024 04:50",
          "link": "https://github.com/khulnasoft/codetypo-validator",
          "publishedOn": "2024-09-24T04:50:29.000Z",
          "wordCount": 2271,
          "title": "khulnasoft added FortiShield to khulnasoft/codetypo-validator",
          "imageUrl": "https://opengraph.githubassets.com/ed287138f03f0df756935c5038c60d4561b12f98c4815b926016c6faa8c75853/khulnasoft/codetypo-validator"
        },
        {
          "id": "https://github.com/khulnasoft/codetypo-action",
          "author": null,
          "description": "khulnasoft\n      \n      added\n      FortiShield\n      to\n      khulnasoft/codetypo-actions\n      \n        · September 24, 2024 04:26",
          "link": "https://github.com/khulnasoft/codetypo-action",
          "publishedOn": "2024-09-24T04:26:13.000Z",
          "wordCount": 4119,
          "title": "khulnasoft added FortiShield to khulnasoft/codetypo-actions",
          "imageUrl": "https://opengraph.githubassets.com/d4a4aafa2b058d11b206920fb20c1489f1793705de4beda1a8cdb8dc55dd5a66/khulnasoft/codetypo-actions"
        },
        {
          "id": "https://github.com/khulnasoft/codetypo",
          "author": null,
          "description": "khulnasoft\n      \n      added\n      FortiShield\n      to\n      khulnasoft/codetypo\n      \n        · September 24, 2024 04:00",
          "link": "https://github.com/khulnasoft/codetypo",
          "publishedOn": "2024-09-24T04:00:26.000Z",
          "wordCount": 6923,
          "title": "khulnasoft added FortiShield to khulnasoft/codetypo",
          "imageUrl": "https://opengraph.githubassets.com/1a0510de4bd625a018f05f8a03741abdc6bd196818460235818735a915f7ba9b/khulnasoft/codetypo"
        },
        {
          "id": "https://github.com/khulnasoft/go-licenses",
          "author": null,
          "description": "khulnasoft\n          \n          forked\n          khulnasoft/go-licenses\n          from\n          google/go-licenses\n          \n            · September 22, 2024 23:34\n          \n        \ngoogle/go-licenses\n          \nA lightweight tool to report on the licenses used by a Go package and its dependencies. Highlight! Versioned external URL to licenses can be found …\n\n  Go\n\n\n              \n\n              \n                  \n                    \n    \n\n821\n              \n\n              \n                1 issue needs help\n              \n\n              Updated Sep 9",
          "link": "https://github.com/khulnasoft/go-licenses",
          "publishedOn": "2024-09-22T23:34:21.000Z",
          "wordCount": 2388,
          "title": "khulnasoft forked khulnasoft/go-licenses from google/go-licenses",
          "imageUrl": "https://opengraph.githubassets.com/45ea11239ddb9d56ef156f7dee6fbaebf81230dd6e38ad67d6e0a8295d917d3a/khulnasoft/go-licenses"
        },
        {
          "id": "https://github.com/khulnasoft/trivy",
          "author": null,
          "description": "khulnasoft\n          \n          forked\n          khulnasoft/trivy\n          from\n          aquasecurity/trivy\n          \n            · September 22, 2024 14:46\n          \n        \naquasecurity/trivy\n          \nFind vulnerabilities, misconfigurations, secrets, SBOM in containers, Kubernetes, code repositories, clouds and more\n\n  Go\n\n\n              \n\n              \n                  \n                    \n    \n\n22.9k\n              \n\n              \n                19 issues need help\n              \n\n              Updated Sep 20",
          "link": "https://github.com/khulnasoft/trivy",
          "publishedOn": "2024-09-22T14:46:29.000Z",
          "wordCount": 3630,
          "title": "khulnasoft forked khulnasoft/trivy from aquasecurity/trivy",
          "imageUrl": "https://opengraph.githubassets.com/15c79a2858789e985138b18843a989121f12c86cfe2382ee55690d9a2f120382/khulnasoft/trivy"
        },
        {
          "id": "https://github.com/khulnasoft/eval",
          "author": null,
          "description": "khulnasoft\n      \n      added\n      FortiShield\n      to\n      khulnasoft/eval\n      \n        · September 11, 2024 01:59",
          "link": "https://github.com/khulnasoft/eval",
          "publishedOn": "2024-09-11T01:59:19.000Z",
          "wordCount": 1681,
          "title": "khulnasoft added FortiShield to khulnasoft/eval",
          "imageUrl": "https://opengraph.githubassets.com/1578496ec6aaf64581e62a36c8aeaf8740e6d8b36a7608ac70571627ca3fa423/khulnasoft/eval"
        },
        {
          "id": "https://github.com/khulnasoft/eval",
          "author": null,
          "description": "khulnasoft\n          \n          forked\n          khulnasoft/eval\n          from\n          openai/human-eval\n          \n            · September 11, 2024 01:59\n          \n        \nopenai/human-eval\n          \nCode for the paper \"Evaluating Large Language Models Trained on Code\"\n\n  Python\n\n\n              \n\n              \n                  \n                    \n    \n\n2.3k\n              \n\n\n              Updated Feb 5",
          "link": "https://github.com/khulnasoft/eval",
          "publishedOn": "2024-09-11T01:59:19.000Z",
          "wordCount": 1681,
          "title": "khulnasoft forked khulnasoft/eval from openai/human-eval",
          "imageUrl": "https://opengraph.githubassets.com/1578496ec6aaf64581e62a36c8aeaf8740e6d8b36a7608ac70571627ca3fa423/khulnasoft/eval"
        },
        {
          "id": "https://github.com/khulnasoft/code-server",
          "author": null,
          "description": "khulnasoft\n          \n          forked\n          khulnasoft/code-server\n          from\n          khulnasoft-lab/code-server\n          \n            · September 8, 2024 16:39\n          \n        \nkhulnasoft-lab/code-server\n          \nVS Code in the browser\nUpdated Sep 6",
          "link": "https://github.com/khulnasoft/code-server",
          "publishedOn": "2024-09-08T16:39:09.000Z",
          "wordCount": 3072,
          "title": "khulnasoft forked khulnasoft/code-server from khulnasoft-lab/code-server",
          "imageUrl": "https://opengraph.githubassets.com/86afff4098f83475c087e2b14be56754099b788067e51541ac9600688a07b52f/khulnasoft/code-server"
        },
        {
          "id": "https://github.com/khulnasoft/edgedb",
          "author": null,
          "description": "khulnasoft\n      \n      added\n      FortiShield\n      to\n      khulnasoft/edgedb\n      \n        · September 7, 2024 10:32",
          "link": "https://github.com/khulnasoft/edgedb",
          "publishedOn": "2024-09-07T10:32:22.000Z",
          "wordCount": 2551,
          "title": "khulnasoft added FortiShield to khulnasoft/edgedb",
          "imageUrl": "https://opengraph.githubassets.com/b910538d8a5c6a8a9fd4991ce9c9a5828a13eb08276a8e66abba3eccbc28f2e0/khulnasoft/edgedb"
        },
        {
          "id": "https://github.com/khulnasoft/vscode-server",
          "author": null,
          "description": "khulnasoft\n          \n          forked\n          khulnasoft/vscode-server\n          from\n          khulnasoft-lab/code-server\n          \n            · September 6, 2024 23:34\n          \n        \nkhulnasoft-lab/code-server\n          \nVS Code in the browser\nUpdated Sep 6",
          "link": "https://github.com/khulnasoft/vscode-server",
          "publishedOn": "2024-09-06T23:34:17.000Z",
          "wordCount": 3072,
          "title": "khulnasoft forked khulnasoft/vscode-server from khulnasoft-lab/code-server",
          "imageUrl": "https://opengraph.githubassets.com/dca5f29310c7ddcebe796e8cd01426414d8e8f9ec657ae9a6c956e0ce80440e2/khulnasoft/vscode-server"
        },
        {
          "id": "https://github.com/khulnasoft/dockerfiles",
          "author": null,
          "description": "khulnasoft\n          \n          forked\n          khulnasoft/dockerfiles\n          from\n          tianon/dockerfiles\n          \n            · September 4, 2024 20:35\n          \n        \ntianon/dockerfiles\n          \nA semi-random collection of odds and ends.\n\n  Dockerfile\n\n\n              \n\n              \n                  \n                    \n    \n\n1.1k\n              \n\n\n              Updated Sep 5",
          "link": "https://github.com/khulnasoft/dockerfiles",
          "publishedOn": "2024-09-04T20:35:07.000Z",
          "wordCount": null,
          "title": "khulnasoft forked khulnasoft/dockerfiles from tianon/dockerfiles",
          "imageUrl": null
        },
        {
          "id": "https://github.com/khulnasoft/slack",
          "author": null,
          "description": "khulnasoft\n      \n      added\n      FortiShield\n      to\n      khulnasoft/slack\n      \n        · August 26, 2024 16:36",
          "link": "https://github.com/khulnasoft/slack",
          "publishedOn": "2024-08-26T16:36:57.000Z",
          "wordCount": 2289,
          "title": "khulnasoft added FortiShield to khulnasoft/slack",
          "imageUrl": "https://opengraph.githubassets.com/51dd506e8113b963a674e1e2f51db70c516159cc7bdea9d9add9e6ab71ef8b07/khulnasoft/slack"
        },
        {
          "id": "https://github.com/khulnasoft/wrk2",
          "author": null,
          "description": "khulnasoft\n          \n          forked\n          khulnasoft/wrk2\n          from\n          kinvolk/wrk2\n          \n            · August 26, 2024 01:41\n          \n        \nkinvolk/wrk2\n          \nA constant throughput, correct latency recording variant of wrk\n\n  C\n\n\n              \n\n              \n                  \n                    \n    \n\n16\n              \n\n\n              Updated Jun 6, 2023",
          "link": "https://github.com/khulnasoft/wrk2",
          "publishedOn": "2024-08-26T01:41:43.000Z",
          "wordCount": 11113,
          "title": "khulnasoft forked khulnasoft/wrk2 from kinvolk/wrk2",
          "imageUrl": "https://opengraph.githubassets.com/21efbecd9e12649313d596066a0e5137ff4a3819fa5c57b31acc903ba47ae24b/khulnasoft/wrk2"
        },
        {
          "id": "https://github.com/khulnasoft/Tiger",
          "author": null,
          "description": "khulnasoft\n      \n      added\n      FortiShield\n      to\n      khulnasoft/Tiger\n      \n        · August 25, 2024 05:30",
          "link": "https://github.com/khulnasoft/Tiger",
          "publishedOn": "2024-08-25T05:30:06.000Z",
          "wordCount": 6002,
          "title": "khulnasoft added FortiShield to khulnasoft/Tiger",
          "imageUrl": "https://opengraph.githubassets.com/5ee907044c1cbb7fc28470a6dd013f6e66f9dab48cf8af2a86033d2df1bc2b2e/khulnasoft/Tiger"
        },
        {
          "id": "https://github.com/khulnasoft/Tiger",
          "author": null,
          "description": "khulnasoft\n          \n          forked\n          khulnasoft/Tiger\n          from\n          Upsonic/Tiger\n          \n            · August 25, 2024 05:30\n          \n        \nUpsonic/Tiger\n          \nNeuralink for your AI Agents - LangChain - Autogen - CrewAI\n\n  Python\n\n\n              \n\n              \n                  \n                    \n    \n\n372\n              \n\n\n              Updated Aug 16",
          "link": "https://github.com/khulnasoft/Tiger",
          "publishedOn": "2024-08-25T05:30:05.000Z",
          "wordCount": 6002,
          "title": "khulnasoft forked khulnasoft/Tiger from Upsonic/Tiger",
          "imageUrl": "https://opengraph.githubassets.com/5ee907044c1cbb7fc28470a6dd013f6e66f9dab48cf8af2a86033d2df1bc2b2e/khulnasoft/Tiger"
        },
        {
          "id": "https://github.com/khulnasoft/js-python-ast",
          "author": null,
          "description": "khulnasoft\n          \n          forked\n          khulnasoft/js-python-ast\n          from\n          lexanth/python-ast\n          \n            · August 13, 2024 06:59\n          \n        \nlexanth/python-ast\n          \n Python (3) Parser for JavaScript/TypeScript (based on antlr4ts) \n\n  TypeScript\n\n\n              \n\n              \n                  \n                    \n    \n\n14\n              \n\n\n              Updated Aug 6, 2020",
          "link": "https://github.com/khulnasoft/js-python-ast",
          "publishedOn": "2024-08-13T06:59:41.000Z",
          "wordCount": 2147,
          "title": "khulnasoft forked khulnasoft/js-python-ast from lexanth/python-ast",
          "imageUrl": "https://opengraph.githubassets.com/686c0b5017800ced1f8057a2dfb4a6fc08525658b5ea1d9d4622bac647e19a56/khulnasoft/js-python-ast"
        }
      ]
    }
  ],
  "cliVersion": "1.15.1"
}